setup.py
django_email_multibackend/__init__.py
django_email_multibackend/backends.py
django_email_multibackend/conditions.py
django_email_multibackend/conf.py
django_email_multibackend/test_settings.py
django_email_multibackend/tests.py
django_email_multibackend.egg-info/PKG-INFO
django_email_multibackend.egg-info/SOURCES.txt
django_email_multibackend.egg-info/dependency_links.txt
django_email_multibackend.egg-info/pbr.json
django_email_multibackend.egg-info/top_level.txt