Metadata-Version: 1.1
Name: django-email-multibackend
Version: 0.5.1
Summary: 
